greynoiselabs/__init__.py
greynoiselabs/api/__init__.py
greynoiselabs/api/async_base_client.py
greynoiselabs/api/base_model.py
greynoiselabs/api/client.py
greynoiselabs/api/enums.py
greynoiselabs/api/exceptions.py
greynoiselabs/api/generate_g_n_q_l.py
greynoiselabs/api/get_c2s.py
greynoiselabs/api/get_i_ps.py
greynoiselabs/api/get_knocks.py
greynoiselabs/api/get_noise_ranks.py
greynoiselabs/api/get_payloads.py
greynoiselabs/api/get_pivot.py
greynoiselabs/api/get_requests.py
greynoiselabs/api/input_types.py
greynoiselabs/cli/__init__.py
greynoiselabs/cli/auth.py
greynoiselabs/cli/main.py
greynoiselabs-0.1.38.dist-info/LICENSE
greynoiselabs-0.1.38.dist-info/METADATA
greynoiselabs-0.1.38.dist-info/WHEEL
greynoiselabs-0.1.38.dist-info/entry_points.txt
greynoiselabs-0.1.38.dist-info/RECORD
