Metadata-Version: 2.1
Name: greynoiselabs
Version: 0.1.38
Summary: Abstraction to interact with GreyNoise Labs GraphQL API.
Home-page: https://api.labs.greynoise.io/
License: MIT
Keywords: internet,scanning,threat intelligence,security
Author: GreyNoise Intelligence
Author-email: labs@greynoise.io
Requires-Python: >=3.8,<4
Classifier: Development Status :: 4 - Beta
Classifier: Intended Audience :: Developers
Classifier: License :: OSI Approved :: MIT License
Classifier: Natural Language :: English
Classifier: Programming Language :: Python
Classifier: Programming Language :: Python :: 3
Classifier: Programming Language :: Python :: 3.8
Classifier: Programming Language :: Python :: 3.9
Classifier: Programming Language :: Python :: 3.10
Classifier: Programming Language :: Python :: 3.11
Classifier: Topic :: Software Development :: Libraries
Requires-Dist: Click (==8.1.7)
Requires-Dist: PyJWT (==2.7.0)
Requires-Dist: auth0-python (==4.4.0)
Requires-Dist: colorama (==0.4.6)
Requires-Dist: httpx (==0.24.1)
Requires-Dist: jsonlines (==3.1.0)
Requires-Dist: merge_args (==0.1.5)
Requires-Dist: platformdirs (==3.9.1)
Requires-Dist: pydantic (==2.0.0)
Requires-Dist: pyperclip (==1.8.2)
Requires-Dist: requests (==2.31.0)
Requires-Dist: requests-oauthlib (==1.3.1)
Requires-Dist: rich (==13.4.2)
Requires-Dist: typer (==0.9.0)
Requires-Dist: urllib3 (==2.0.6)
Requires-Dist: websockets (==11.0.3)
Project-URL: Documentation, https://api.labs.greynoise.io/
Project-URL: Repository, https://github.com/GreyNoise-Intelligence/greynoiselabs
